GenPackageDoc/CDocBuilder.py
GenPackageDoc/CInterface.py
GenPackageDoc/CPackageDocConfig.py
GenPackageDoc/CPatterns.py
GenPackageDoc/CSourceParser.py
GenPackageDoc/GenPackageDoc.pdf
GenPackageDoc/__init__.py
GenPackageDoc/version.py
GenPackageDoc/styles/admonitions.sty
GenPackageDoc/styles/common.sty
GenPackageDoc/styles/docutils.sty
GenPackageDoc/styles/preamble.tex
GenPackageDoc/styles/robotframeworkaio.sty
genpackagedoc-0.42.0.dist-info/licenses/LICENSE
genpackagedoc-0.42.0.dist-info/METADATA
genpackagedoc-0.42.0.dist-info/WHEEL
genpackagedoc-0.42.0.dist-info/top_level.txt
genpackagedoc-0.42.0.dist-info/RECORD
