Metadata-Version: 2.4
Name: GenPackageDoc
Version: 0.42.0
Summary: Documentation builder for Python packages
Home-page: https://github.com/test-fullautomation/python-genpackagedoc
Author: Holger Queckenstedt
Author-email: Holger.Queckenstedt@de.bosch.com
Classifier: Programming Language :: Python :: 3
Classifier: License :: OSI Approved :: Apache Software License
Classifier: Operating System :: OS Independent
Classifier: Development Status :: 3 - Alpha
Classifier: Intended Audience :: Developers
Classifier: Topic :: Software Development
Requires-Python: >=3.0
License-File: LICENSE
Requires-Dist: pypandoc
Requires-Dist: colorama
Requires-Dist: PythonExtensionsCollection
Dynamic: author
Dynamic: author-email
Dynamic: classifier
Dynamic: description
Dynamic: description-content-type
Dynamic: home-page
Dynamic: license-file
Dynamic: requires-dist
Dynamic: requires-python
Dynamic: summary
